package_format_tools/__init__.py
package_format_tools-0.1.0a0.dist-info/METADATA
package_format_tools-0.1.0a0.dist-info/WHEEL
package_format_tools-0.1.0a0.dist-info/RECORD
